simplebbox/__init__.py
simplebbox/_array_processor.py
simplebbox/array.py
simplebbox/numpy_array.py
simplebbox/torch_tensor.py
simplebbox-0.0.10.dist-info/AUTHORS.rst
simplebbox-0.0.10.dist-info/LICENSE
simplebbox-0.0.10.dist-info/METADATA
simplebbox-0.0.10.dist-info/WHEEL
simplebbox-0.0.10.dist-info/top_level.txt
simplebbox-0.0.10.dist-info/RECORD
