Metadata-Version: 2.1
Name: simplebbox
Version: 0.0.10
Summary: Functions for bounding box processing
Home-page: https://github.com/serge-m/simplebbox
Author: Sergey Matyunin
Author-email: serge-m@users.noreply.github.com
License: MIT license
Keywords: simplebbox
Platform: UNKNOWN
Classifier: Development Status :: 2 - Pre-Alpha
Classifier: Intended Audience :: Developers
Classifier: License :: OSI Approved :: MIT License
Classifier: Natural Language :: English
Classifier: Programming Language :: Python :: 3
Classifier: Programming Language :: Python :: 3.6
Classifier: Programming Language :: Python :: 3.7
Classifier: Programming Language :: Python :: 3.8
Requires-Python: >=3.6
